spanit/__init__.py
spanit/__main__.py
spanit/py.typed
spanit-0.1.0.dist-info/METADATA
spanit-0.1.0.dist-info/WHEEL
spanit-0.1.0.dist-info/licenses/LICENSE.txt
spanit-0.1.0.dist-info/RECORD
