Metadata-Version: 2.1
Name: spanit
Version: 0.1.0
Summary: Mesure and instrument code using spans
Project-URL: homepage, https://github.com/itay-raveh/spanit
Author-email: Itay Raveh <itay.raveh+spanit@proton.me>
License: 
License-File: LICENSE.txt
Requires-Python: >=3.8
